src/.DS_Store
src/.gitignore
src/README.md
src/apps/app1/__init__.py
src/apps/app1/controllers.py
src/apps/app1/models.py
src/apps/app1/routes.py
src/apps/app1/tests/__init__.py
src/apps/app1/tests/test_app1.py
src/apps/app1/utils.py
src/apps/app1/views.py
src/apps/app2/__init__.py
src/apps/app2/controllers.py
src/apps/app2/models.py
src/apps/app2/routes.py
src/apps/app2/tests/__init__.py
src/apps/app2/tests/test_app2.py
src/apps/app2/views.py
src/config/__init__.py
src/config/db_config.py
src/config/settings.py
src/db/__init__.py
src/db/create_tables.py
src/db/db_config.py
src/db/delete_table.py
src/db/generate_schema.py
src/db/insert_data.py
src/db/schema.py
src/db/test.xlsx
src/db/update_table.py
src/db/validators.py
src/db/xls_reader.py
src/docs/db_readme.md
src/libs/Scale_down.py
src/libs/Scale_up.py
src/requirements.txt
src/run.py
src/templates/home.html
src/tests/__init__.py
src/tests/test_all.py
src/utils/__init__.py
src/utils/create_dummy_data.py
src/utils/utility_scripts.py
conc_automation_test_tool-0.2.0.dist-info/METADATA
conc_automation_test_tool-0.2.0.dist-info/WHEEL
conc_automation_test_tool-0.2.0.dist-info/RECORD
