Metadata-Version: 2.3
Name: conc_automation_test_tool
Version: 0.2.0
Summary: 
Author: gracious7
Author-email: princetripathi093@gmail.com
Requires-Python: >=3.13
Classifier: Programming Language :: Python :: 3
Classifier: Programming Language :: Python :: 3.13
